{
  "generated_at": "2026-07-24T18:29:58.423Z",
  "winning_feature": {
    "input": "tap",
    "control": "touch",
    "sound": "sound",
    "engine": "viral"
  },
  "hot_circuit": "04-loss",
  "cold_circuit": "08-garden",
  "engine_tilt": "calm",
  "top_movers": [
    {
      "game": "unknown",
      "attention_change_pct": 0,
      "latest_min": 0,
      "visitors": 7
    },
    {
      "game": "follower-flood",
      "attention_change_pct": 0,
      "latest_min": 0,
      "visitors": 1
    },
    {
      "game": "streak-flame",
      "attention_change_pct": 0,
      "latest_min": 0,
      "visitors": 1
    },
    {
      "game": "infinite-fall",
      "attention_change_pct": 0,
      "latest_min": 0,
      "visitors": 1
    },
    {
      "game": "filter-shift",
      "attention_change_pct": 0,
      "latest_min": 0,
      "visitors": 1
    }
  ],
  "concepts": [
    {
      "id": "rescue-autoplay-chicken",
      "source": "rescue_bottom",
      "generated_at": "2026-07-24T18:29:58.423Z",
      "engine": "viral",
      "input": "tap",
      "face_control": false,
      "has_sound": true,
      "primary_circuit": "near_miss_reward",
      "rationale": "Rescue lowest P+D game autoplay-chicken (P=42, D=0) by swapping loop and adding sound.",
      "rescue_target": "autoplay-chicken",
      "prompt_seed": "Rescue the game \"Autoplay Chicken\". Keep core mechanic, replace weakest loop with near_miss_reward, add audio feedback, tighten first-tap payoff, cap session to 60s."
    },
    {
      "id": "loop-mrz9yzo6-0",
      "source": "feed_analytics",
      "generated_at": "2026-07-24T18:29:58.422Z",
      "engine": "calm",
      "input": "tap",
      "face_control": false,
      "has_sound": true,
      "primary_circuit": "04-loss",
      "rationale": "Best feature=tap/touch/sound/viral, hot circuit=04-loss, cold circuit=08-garden, engine share=1; promote under-tested combos.",
      "from_movers": [
        "unknown",
        "follower-flood",
        "streak-flame",
        "infinite-fall",
        "filter-shift"
      ],
      "prompt_seed": "Build a one-tap browser mini-game. Engine: calm. Input: tap. Primary loop: 04-loss. Sound: required. Single session <90s. No install. Use existing game mechanics from top mover unknown."
    },
    {
      "id": "loop-mrz9yzo7-1",
      "source": "feed_analytics",
      "generated_at": "2026-07-24T18:29:58.423Z",
      "engine": "calm",
      "input": "drag",
      "face_control": false,
      "has_sound": true,
      "primary_circuit": "04-loss",
      "rationale": "Best feature=tap/touch/sound/viral, hot circuit=04-loss, cold circuit=08-garden, engine share=1; promote under-tested combos.",
      "from_movers": [
        "unknown",
        "follower-flood",
        "streak-flame",
        "infinite-fall",
        "filter-shift"
      ],
      "prompt_seed": "Build a one-tap browser mini-game. Engine: calm. Input: drag. Primary loop: 04-loss. Sound: required. Single session <90s. No install. Use existing game mechanics from top mover unknown."
    },
    {
      "id": "loop-mrz9yzo7-2",
      "source": "feed_analytics",
      "generated_at": "2026-07-24T18:29:58.423Z",
      "engine": "viral",
      "input": "tap",
      "face_control": true,
      "has_sound": true,
      "primary_circuit": "04-loss",
      "rationale": "Best feature=tap/touch/sound/viral, hot circuit=04-loss, cold circuit=08-garden, engine share=1; promote under-tested combos.",
      "from_movers": [
        "unknown",
        "follower-flood",
        "streak-flame",
        "infinite-fall",
        "filter-shift"
      ],
      "prompt_seed": "Build a one-tap browser mini-game. Engine: viral. Input: tap with face-control fallback. Primary loop: 04-loss. Sound: required. Single session <90s. No install. Use existing game mechanics from top mover unknown."
    },
    {
      "id": "loop-mrz9yzo7-3",
      "source": "feed_analytics",
      "generated_at": "2026-07-24T18:29:58.423Z",
      "engine": "calm",
      "input": "tap",
      "face_control": false,
      "has_sound": false,
      "primary_circuit": "04-loss",
      "rationale": "Best feature=tap/touch/sound/viral, hot circuit=04-loss, cold circuit=08-garden, engine share=1; promote under-tested combos.",
      "from_movers": [
        "unknown",
        "follower-flood",
        "streak-flame",
        "infinite-fall",
        "filter-shift"
      ],
      "prompt_seed": "Build a one-tap browser mini-game. Engine: calm. Input: tap. Primary loop: 04-loss. Sound: silent OK. Single session <90s. No install. Use existing game mechanics from top mover unknown."
    },
    {
      "id": "loop-mrz9yzo7-4",
      "source": "feed_analytics",
      "generated_at": "2026-07-24T18:29:58.423Z",
      "engine": "viral",
      "input": "tap",
      "face_control": false,
      "has_sound": true,
      "primary_circuit": "08-garden",
      "rationale": "Best feature=tap/touch/sound/viral, hot circuit=04-loss, cold circuit=08-garden, engine share=1; promote under-tested combos.",
      "from_movers": [
        "unknown",
        "follower-flood",
        "streak-flame",
        "infinite-fall",
        "filter-shift"
      ],
      "prompt_seed": "Build a one-tap browser mini-game. Engine: viral. Input: tap. Primary loop: 08-garden. Sound: required. Single session <90s. No install. Use existing game mechanics from top mover unknown."
    },
    {
      "id": "loop-mrz9yzo7-5",
      "source": "feed_analytics",
      "generated_at": "2026-07-24T18:29:58.423Z",
      "engine": "calm",
      "input": "tap",
      "face_control": false,
      "has_sound": true,
      "primary_circuit": "04-loss",
      "rationale": "Best feature=tap/touch/sound/viral, hot circuit=04-loss, cold circuit=08-garden, engine share=1; promote under-tested combos.",
      "from_movers": [
        "unknown",
        "follower-flood",
        "streak-flame",
        "infinite-fall",
        "filter-shift"
      ],
      "prompt_seed": "Build a one-tap browser mini-game. Engine: calm. Input: tap. Primary loop: 04-loss. Sound: required. Single session <90s. No install. Use existing game mechanics from top mover unknown."
    }
  ]
}